{"nodes": [{"id": "appointmentslot", "label": "AppointmentSlot.php", "file_type": "code", "source_file": "Model\\AppointmentSlot.php", "source_location": "L1"}, {"id": "appointmentslot_appointmentslot", "label": "AppointmentSlot", "file_type": "code", "source_file": "Model\\AppointmentSlot.php", "source_location": "L7"}, {"id": "appointmentslot_appointmentslot_construct", "label": ".__construct()", "file_type": "code", "source_file": "Model\\AppointmentSlot.php", "source_location": "L18"}, {"id": "appointmentslot_appointmentslot_getid", "label": ".getId()", "file_type": "code", "source_file": "Model\\AppointmentSlot.php", "source_location": "L33"}, {"id": "appointmentslot_appointmentslot_getagentid", "label": ".getAgentId()", "file_type": "code", "source_file": "Model\\AppointmentSlot.php", "source_location": "L34"}, {"id": "appointmentslot_appointmentslot_getservicetype", "label": ".getServiceType()", "file_type": "code", "source_file": "Model\\AppointmentSlot.php", "source_location": "L35"}, {"id": "appointmentslot_appointmentslot_getdayofweek", "label": ".getDayOfWeek()", "file_type": "code", "source_file": "Model\\AppointmentSlot.php", "source_location": "L36"}, {"id": "appointmentslot_appointmentslot_getstarttime", "label": ".getStartTime()", "file_type": "code", "source_file": "Model\\AppointmentSlot.php", "source_location": "L37"}, {"id": "appointmentslot_appointmentslot_getendtime", "label": ".getEndTime()", "file_type": "code", "source_file": "Model\\AppointmentSlot.php", "source_location": "L38"}, {"id": "appointmentslot_appointmentslot_isactive", "label": ".isActive()", "file_type": "code", "source_file": "Model\\AppointmentSlot.php", "source_location": "L39"}, {"id": "appointmentslot_appointmentslot_jsonserialize", "label": ".jsonSerialize()", "file_type": "code", "source_file": "Model\\AppointmentSlot.php", "source_location": "L41"}, {"id": "appointmentslot_appointmentslot_toarray", "label": ".toArray()", "file_type": "code", "source_file": "Model\\AppointmentSlot.php", "source_location": "L45"}, {"id": "appointmentslot_appointmentslot_fromrow", "label": ".fromRow()", "file_type": "code", "source_file": "Model\\AppointmentSlot.php", "source_location": "L60"}], "edges": [{"source": "appointmentslot", "target": "appointmentslot_appointmentslot", "relation": "contains", "confidence": "EXTRACTED", "source_file": "Model\\AppointmentSlot.php", "source_location": "L7", "weight": 1.0}, {"source": "appointmentslot_appointmentslot", "target": "appointmentslot_appointmentslot_construct", "relation": "method", "confidence": "EXTRACTED", "source_file": "Model\\AppointmentSlot.php", "source_location": "L18", "weight": 1.0}, {"source": "appointmentslot_appointmentslot", "target": "appointmentslot_appointmentslot_getid", "relation": "method", "confidence": "EXTRACTED", "source_file": "Model\\AppointmentSlot.php", "source_location": "L33", "weight": 1.0}, {"source": "appointmentslot_appointmentslot", "target": "appointmentslot_appointmentslot_getagentid", "relation": "method", "confidence": "EXTRACTED", "source_file": "Model\\AppointmentSlot.php", "source_location": "L34", "weight": 1.0}, {"source": "appointmentslot_appointmentslot", "target": "appointmentslot_appointmentslot_getservicetype", "relation": "method", "confidence": "EXTRACTED", "source_file": "Model\\AppointmentSlot.php", "source_location": "L35", "weight": 1.0}, {"source": "appointmentslot_appointmentslot", "target": "appointmentslot_appointmentslot_getdayofweek", "relation": "method", "confidence": "EXTRACTED", "source_file": "Model\\AppointmentSlot.php", "source_location": "L36", "weight": 1.0}, {"source": "appointmentslot_appointmentslot", "target": "appointmentslot_appointmentslot_getstarttime", "relation": "method", "confidence": "EXTRACTED", "source_file": "Model\\AppointmentSlot.php", "source_location": "L37", "weight": 1.0}, {"source": "appointmentslot_appointmentslot", "target": "appointmentslot_appointmentslot_getendtime", "relation": "method", "confidence": "EXTRACTED", "source_file": "Model\\AppointmentSlot.php", "source_location": "L38", "weight": 1.0}, {"source": "appointmentslot_appointmentslot", "target": "appointmentslot_appointmentslot_isactive", "relation": "method", "confidence": "EXTRACTED", "source_file": "Model\\AppointmentSlot.php", "source_location": "L39", "weight": 1.0}, {"source": "appointmentslot_appointmentslot", "target": "appointmentslot_appointmentslot_jsonserialize", "relation": "method", "confidence": "EXTRACTED", "source_file": "Model\\AppointmentSlot.php", "source_location": "L41", "weight": 1.0}, {"source": "appointmentslot_appointmentslot", "target": "appointmentslot_appointmentslot_toarray", "relation": "method", "confidence": "EXTRACTED", "source_file": "Model\\AppointmentSlot.php", "source_location": "L45", "weight": 1.0}, {"source": "appointmentslot_appointmentslot", "target": "appointmentslot_appointmentslot_fromrow", "relation": "method", "confidence": "EXTRACTED", "source_file": "Model\\AppointmentSlot.php", "source_location": "L60", "weight": 1.0}, {"source": "appointmentslot_appointmentslot_jsonserialize", "target": "appointmentslot_appointmentslot_toarray", "relation": "calls", "confidence": "EXTRACTED", "source_file": "Model\\AppointmentSlot.php", "source_location": "L42", "weight": 1.0}]}