{"nodes": [{"id": "maincontroller", "label": "MainController.php", "file_type": "code", "source_file": "Controller\\MainController.php", "source_location": "L1"}, {"id": "maincontroller_maincontroller", "label": "MainController", "file_type": "code", "source_file": "Controller\\MainController.php", "source_location": "L17"}, {"id": "maincontroller_maincontroller_authorize", "label": ".authorize()", "file_type": "code", "source_file": "Controller\\MainController.php", "source_location": "L22"}, {"id": "maincontroller_maincontroller_showdata", "label": ".showData()", "file_type": "code", "source_file": "Controller\\MainController.php", "source_location": "L95"}, {"id": "maincontroller_maincontroller_handlerequest", "label": ".handleRequest()", "file_type": "code", "source_file": "Controller\\MainController.php", "source_location": "L103"}, {"id": "maincontroller_maincontroller_getdb", "label": ".getDb()", "file_type": "code", "source_file": "Controller\\MainController.php", "source_location": "L246"}, {"id": "maincontroller_maincontroller_listtransporttypes", "label": ".listTransportTypes()", "file_type": "code", "source_file": "Controller\\MainController.php", "source_location": "L251"}, {"id": "maincontroller_maincontroller_listtransports", "label": ".listTransports()", "file_type": "code", "source_file": "Controller\\MainController.php", "source_location": "L256"}, {"id": "maincontroller_maincontroller_showtransport", "label": ".showTransport()", "file_type": "code", "source_file": "Controller\\MainController.php", "source_location": "L263"}, {"id": "maincontroller_maincontroller_addtransport", "label": ".addTransport()", "file_type": "code", "source_file": "Controller\\MainController.php", "source_location": "L273"}, {"id": "maincontroller_maincontroller_updatetransport", "label": ".updateTransport()", "file_type": "code", "source_file": "Controller\\MainController.php", "source_location": "L296"}, {"id": "maincontroller_maincontroller_deletetransport", "label": ".deleteTransport()", "file_type": "code", "source_file": "Controller\\MainController.php", "source_location": "L322"}, {"id": "maincontroller_maincontroller_listtrajets", "label": ".listTrajets()", "file_type": "code", "source_file": "Controller\\MainController.php", "source_location": "L327"}, {"id": "maincontroller_maincontroller_listtrajetsbytypeandsort", "label": ".listTrajetsByTypeAndSort()", "file_type": "code", "source_file": "Controller\\MainController.php", "source_location": "L334"}, {"id": "maincontroller_maincontroller_addtrajet", "label": ".addTrajet()", "file_type": "code", "source_file": "Controller\\MainController.php", "source_location": "L347"}, {"id": "maincontroller_maincontroller_deletetrajet", "label": ".deleteTrajet()", "file_type": "code", "source_file": "Controller\\MainController.php", "source_location": "L360"}, {"id": "maincontroller_maincontroller_showtrajet", "label": ".showTrajet()", "file_type": "code", "source_file": "Controller\\MainController.php", "source_location": "L364"}, {"id": "maincontroller_maincontroller_getoccupancy", "label": ".getOccupancy()", "file_type": "code", "source_file": "Controller\\MainController.php", "source_location": "L370"}, {"id": "maincontroller_maincontroller_listtickets", "label": ".listTickets()", "file_type": "code", "source_file": "Controller\\MainController.php", "source_location": "L385"}, {"id": "maincontroller_maincontroller_listticketsenriched", "label": ".listTicketsEnriched()", "file_type": "code", "source_file": "Controller\\MainController.php", "source_location": "L392"}, {"id": "maincontroller_maincontroller_addticket", "label": ".addTicket()", "file_type": "code", "source_file": "Controller\\MainController.php", "source_location": "L414"}, {"id": "maincontroller_maincontroller_cancelticket", "label": ".cancelTicket()", "file_type": "code", "source_file": "Controller\\MainController.php", "source_location": "L421"}, {"id": "maincontroller_maincontroller_generateref", "label": ".generateRef()", "file_type": "code", "source_file": "Controller\\MainController.php", "source_location": "L425"}], "edges": [{"source": "maincontroller", "target": "maincontroller_maincontroller", "relation": "contains", "confidence": "EXTRACTED", "source_file": "Controller\\MainController.php", "source_location": "L17", "weight": 1.0}, {"source": "maincontroller_maincontroller", "target": "maincontroller_maincontroller_authorize", "relation": "method", "confidence": "EXTRACTED", "source_file": "Controller\\MainController.php", "source_location": "L22", "weight": 1.0}, {"source": "maincontroller_maincontroller", "target": "maincontroller_maincontroller_showdata", "relation": "method", "confidence": "EXTRACTED", "source_file": "Controller\\MainController.php", "source_location": "L95", "weight": 1.0}, {"source": "maincontroller_maincontroller", "target": "maincontroller_maincontroller_handlerequest", "relation": "method", "confidence": "EXTRACTED", "source_file": "Controller\\MainController.php", "source_location": "L103", "weight": 1.0}, {"source": "maincontroller_maincontroller", "target": "maincontroller_maincontroller_getdb", "relation": "method", "confidence": "EXTRACTED", "source_file": "Controller\\MainController.php", "source_location": "L246", "weight": 1.0}, {"source": "maincontroller_maincontroller", "target": "maincontroller_maincontroller_listtransporttypes", "relation": "method", "confidence": "EXTRACTED", "source_file": "Controller\\MainController.php", "source_location": "L251", "weight": 1.0}, {"source": "maincontroller_maincontroller", "target": "maincontroller_maincontroller_listtransports", "relation": "method", "confidence": "EXTRACTED", "source_file": "Controller\\MainController.php", "source_location": "L256", "weight": 1.0}, {"source": "maincontroller_maincontroller", "target": "maincontroller_maincontroller_showtransport", "relation": "method", "confidence": "EXTRACTED", "source_file": "Controller\\MainController.php", "source_location": "L263", "weight": 1.0}, {"source": "maincontroller_maincontroller", "target": "maincontroller_maincontroller_addtransport", "relation": "method", "confidence": "EXTRACTED", "source_file": "Controller\\MainController.php", "source_location": "L273", "weight": 1.0}, {"source": "maincontroller_maincontroller", "target": "maincontroller_maincontroller_updatetransport", "relation": "method", "confidence": "EXTRACTED", "source_file": "Controller\\MainController.php", "source_location": "L296", "weight": 1.0}, {"source": "maincontroller_maincontroller", "target": "maincontroller_maincontroller_deletetransport", "relation": "method", "confidence": "EXTRACTED", "source_file": "Controller\\MainController.php", "source_location": "L322", "weight": 1.0}, {"source": "maincontroller_maincontroller", "target": "maincontroller_maincontroller_listtrajets", "relation": "method", "confidence": "EXTRACTED", "source_file": "Controller\\MainController.php", "source_location": "L327", "weight": 1.0}, {"source": "maincontroller_maincontroller", "target": "maincontroller_maincontroller_listtrajetsbytypeandsort", "relation": "method", "confidence": "EXTRACTED", "source_file": "Controller\\MainController.php", "source_location": "L334", "weight": 1.0}, {"source": "maincontroller_maincontroller", "target": "maincontroller_maincontroller_addtrajet", "relation": "method", "confidence": "EXTRACTED", "source_file": "Controller\\MainController.php", "source_location": "L347", "weight": 1.0}, {"source": "maincontroller_maincontroller", "target": "maincontroller_maincontroller_deletetrajet", "relation": "method", "confidence": "EXTRACTED", "source_file": "Controller\\MainController.php", "source_location": "L360", "weight": 1.0}, {"source": "maincontroller_maincontroller", "target": "maincontroller_maincontroller_showtrajet", "relation": "method", "confidence": "EXTRACTED", "source_file": "Controller\\MainController.php", "source_location": "L364", "weight": 1.0}, {"source": "maincontroller_maincontroller", "target": "maincontroller_maincontroller_getoccupancy", "relation": "method", "confidence": "EXTRACTED", "source_file": "Controller\\MainController.php", "source_location": "L370", "weight": 1.0}, {"source": "maincontroller_maincontroller", "target": "maincontroller_maincontroller_listtickets", "relation": "method", "confidence": "EXTRACTED", "source_file": "Controller\\MainController.php", "source_location": "L385", "weight": 1.0}, {"source": "maincontroller_maincontroller", "target": "maincontroller_maincontroller_listticketsenriched", "relation": "method", "confidence": "EXTRACTED", "source_file": "Controller\\MainController.php", "source_location": "L392", "weight": 1.0}, {"source": "maincontroller_maincontroller", "target": "maincontroller_maincontroller_addticket", "relation": "method", "confidence": "EXTRACTED", "source_file": "Controller\\MainController.php", "source_location": "L414", "weight": 1.0}, {"source": "maincontroller_maincontroller", "target": "maincontroller_maincontroller_cancelticket", "relation": "method", "confidence": "EXTRACTED", "source_file": "Controller\\MainController.php", "source_location": "L421", "weight": 1.0}, {"source": "maincontroller_maincontroller", "target": "maincontroller_maincontroller_generateref", "relation": "method", "confidence": "EXTRACTED", "source_file": "Controller\\MainController.php", "source_location": "L425", "weight": 1.0}]}